LifeManager/BM.py
LifeManager/BM.pyi
LifeManager/Cursor.py
LifeManager/LM.py
LifeManager/LM.pyi
LifeManager/TM.py
LifeManager/UI_launcher.py
LifeManager/__init__.py
LifeManager/config.py
LifeManager/logger_config.py
LifeManager/py.typed
LifeManager/telegram_launcher.py
LifeManager/LocalUI/__init__.py
LifeManager/LocalUI/main.py
LifeManager/LocalUI/st_BM.py
LifeManager/LocalUI/st_LM.py
LifeManager/LocalUI/st_home.py
LifeManager/LocalUI/st_log.py
LifeManager/telegram/__init__.py
LifeManager/telegram/telegram.py
lifemanager-1.0.7.dist-info/licenses/LICENSE
lifemanager-1.0.7.dist-info/METADATA
lifemanager-1.0.7.dist-info/WHEEL
lifemanager-1.0.7.dist-info/top_level.txt
lifemanager-1.0.7.dist-info/RECORD
