Metadata-Version: 2.4
Name: LifeManager
Version: 1.0.7
Summary: A simple Python package
Author-email: Raad <alirezzaraadco@gmail.com>
License-Expression: MIT
Project-URL: Homepage, https://github.com/yourusername/LifeManager
Project-URL: Documentation, https://github.com/yourusername/LifeManager/README.md
Project-URL: Repository, https://github.com/yourusername/LifeManager.git
Project-URL: Issues, https://github.com/yourusername/LifeManager/issues
Classifier: Programming Language :: Python :: 3
Classifier: Programming Language :: Python :: 3.12
Classifier: Operating System :: OS Independent
Requires-Python: >=3.12
License-File: LICENSE
Requires-Dist: matplotlib>=3.10.1
Requires-Dist: sqlalchemy>=2.0.40
Requires-Dist: pandas>=2.2.3
Requires-Dist: python-dotenv>=1.1.0
Requires-Dist: psycopg2-binary>=2.9.10
Requires-Dist: openpyxl>=3.1.5
Requires-Dist: aiogram==3.20.0.post0
Requires-Dist: streamlit>=1.46.0
Dynamic: license-file
